spei/__init__.py
spei/_typing.py
spei/_version.py
spei/climdex.py
spei/dist.py
spei/knmi.py
spei/plot.py
spei/py.typed
spei/rai.py
spei/si.py
spei/utils.py
spei-0.8.2.dist-info/licenses/LICENSE
spei-0.8.2.dist-info/METADATA
spei-0.8.2.dist-info/WHEEL
spei-0.8.2.dist-info/top_level.txt
spei-0.8.2.dist-info/RECORD
