Metadata-Version: 2.4
Name: spei
Version: 0.8.2
Summary: A simple Python package to calculate drought indices for time series such as the SPI, SPEI and SGI.
Author-email: Martin Vonk <vonk.mart@gmail.com>
License: MIT License
Project-URL: homepage, https://github.com/martinvonk/spei
Project-URL: repository, https://github.com/martinvonk/spei
Classifier: Programming Language :: Python :: 3 :: Only
Classifier: Programming Language :: Python :: 3.10
Classifier: Programming Language :: Python :: 3.11
Classifier: Programming Language :: Python :: 3.12
Classifier: Programming Language :: Python :: 3.13
Classifier: Programming Language :: Python :: 3.14
Classifier: Topic :: Scientific/Engineering :: Hydrology
Classifier: Intended Audience :: Science/Research
Classifier: License :: OSI Approved :: MIT License
Classifier: Operating System :: OS Independent
Classifier: Typing :: Typed
Requires-Python: >=3.10
License-File: LICENSE
Requires-Dist: numpy
Requires-Dist: scipy
Requires-Dist: matplotlib
Requires-Dist: pandas
Provides-Extra: notebook
Requires-Dist: ipykernel; extra == "notebook"
Requires-Dist: pastas; extra == "notebook"
Requires-Dist: rpy2; extra == "notebook"
Requires-Dist: standard-precip; extra == "notebook"
Requires-Dist: pandas<3.0; extra == "notebook"
Provides-Extra: documentation
Requires-Dist: sphinx>=8.2; extra == "documentation"
Requires-Dist: myst-parser; extra == "documentation"
Requires-Dist: nbsphinx; extra == "documentation"
Provides-Extra: ruffing
Requires-Dist: ruff; extra == "ruffing"
Provides-Extra: typing
Requires-Dist: mypy; extra == "typing"
Requires-Dist: pandas-stubs; extra == "typing"
Provides-Extra: pytesting
Requires-Dist: pytest>=7; extra == "pytesting"
Requires-Dist: pytest-cov; extra == "pytesting"
Requires-Dist: pytest-sugar; extra == "pytesting"
Provides-Extra: coveraging
Requires-Dist: coverage; extra == "coveraging"
Provides-Extra: dev
Requires-Dist: spei[coveraging,pytesting,ruffing,typing]; extra == "dev"
Requires-Dist: tox; extra == "dev"
Dynamic: license-file
